trexanalytics
