Metadata-Version: 2.4
Name: trex_analytic
Version: 1.7.2
Summary: TRex analytics package
Home-page: https://bitbucket.org/lokjac/trex-program
Author: Jack Lok
Author-email: sglok77@gmail.com
Classifier: Programming Language :: Python :: 3
Classifier: License :: OSI Approved :: MIT License
Classifier: Operating System :: OS Independent
Requires-Dist: trex-lib
Requires-Dist: trex-model
Dynamic: author
Dynamic: author-email
Dynamic: classifier
Dynamic: description
Dynamic: description-content-type
Dynamic: home-page
Dynamic: requires-dist
Dynamic: summary
